djangoeditorwidgets/__init__.py
djangoeditorwidgets/apps.py
djangoeditorwidgets/config.py
djangoeditorwidgets/urls.py
djangoeditorwidgets/views.py
djangoeditorwidgets/widgets.py
djangoeditorwidgets/management/__init__.py
djangoeditorwidgets/management/__pycache__/__init__.cpython-38.pyc
djangoeditorwidgets/management/commands/__init__.py
djangoeditorwidgets/management/commands/download_editor_scripts.py
djangoeditorwidgets/management/commands/__pycache__/__init__.cpython-38.pyc
djangoeditorwidgets/management/commands/__pycache__/download_editor_scripts.cpython-38.pyc
djangoeditorwidgets/management/commands/__pycache__/download_editpr_scripts.cpython-38.pyc
djangoeditorwidgets/static/djangoeditorwidgets/monaco/monaco.config.js
djangoeditorwidgets/static/djangoeditorwidgets/monaco/monaco.custom.css
djangoeditorwidgets/static/djangoeditorwidgets/tinymce/tinymce.config.js
djangoeditorwidgets/static/djangoeditorwidgets/tinymce/tinymce.custom.css
djangoeditorwidgets/static/djangoeditorwidgets/tinymce/tinymce.init.js
django_editor_widgets-4.2.dist-info/METADATA
django_editor_widgets-4.2.dist-info/WHEEL
django_editor_widgets-4.2.dist-info/top_level.txt
django_editor_widgets-4.2.dist-info/RECORD
