Metadata-Version: 2.1
Name: django-editor-widgets
Version: 4.2
Summary: Rich web editor widgets in the Django Admin
Home-page: https://github.com/giorgi94/django-editor-widgets
Author: Giorgi Kakulashvili
License: MIT
Keywords: django,monaco,tinymce
Platform: OS Independent
Requires-Dist: Django (>=3.0)
Requires-Dist: Pillow (>=8)
Requires-Dist: requests (>=2)
